{
    "/location/location/contains": "location contains",
    "/location/administrative_division/country": "administrative division of country",
    "/location/country/administrative_divisions": "country of administrative divisions",
    "/business/person/company": "person of company",
    "/people/person/place_lived": "place lived",
    "/people/person/nationality": "nationality",
    "/location/neighborhood/neighborhood_of": "neighborhood of",
    "/people/deceased_person/place_of_death": "place of death",
    "/location/country/capital": "country capital",
    "/people/person/place_of_birth": "place of birth",
    "/business/company/founders": "company founders",
    "/people/person/children": "children",
    "/people/person/religion": "religion",
    "/business/company/place_founded":"company founded place",
    "/business/company/advisors":"company advisors",
    "/people/ethnicity/geographic_distribution": "geographic distribution",
    "/sports/sports_team_location/teams": "sports team location of teams",
    "/sports/sports_team/location": "sports team of location",
    "/business/company_shareholder/major_shareholder_of": "company shareholder among major shareholders",
    "/business/company/major_shareholders": "company major shareholders",
    "/people/person/ethnicity": "ethnicity",
    "/people/ethnicity/people": "ethnicity of people",
    "/people/person/profession": "profession",
    "/business/company/industry": "company industry"
}